FigureEight2018NianShujuKexuejiaBaogao/README.md
FigureEight2018NianShujuKexuejiaBaogao/__init__.py
FigureEight2018NianShujuKexuejiaBaogao/__main__.py
FigureEight2018NianShujuKexuejiaBaogao/file.pdf
FigureEight2018NianShujuKexuejiaBaogao/index.html
figure_eight_2018_nian_shuju_kexuejia_baogao-2024.3.3.0.dist-info/METADATA
figure_eight_2018_nian_shuju_kexuejia_baogao-2024.3.3.0.dist-info/WHEEL
figure_eight_2018_nian_shuju_kexuejia_baogao-2024.3.3.0.dist-info/entry_points.txt
figure_eight_2018_nian_shuju_kexuejia_baogao-2024.3.3.0.dist-info/top_level.txt
figure_eight_2018_nian_shuju_kexuejia_baogao-2024.3.3.0.dist-info/RECORD
